dimencalc/__init__.py
dimencalc/shapes.py
dimencalc/solids.py
dimencalc-1.0.0.dist-info/METADATA
dimencalc-1.0.0.dist-info/WHEEL
dimencalc-1.0.0.dist-info/top_level.txt
dimencalc-1.0.0.dist-info/RECORD
