Metadata-Version: 2.1
Name: dimencalc
Version: 1.0.0
Summary: A Python library to calculate area, perimeter, volume, and surface area
Home-page: https://github.com/Jatly/dimencalc.git
Author: Jatly
Author-email: jatly.aj.29@gmail.com
License: UNKNOWN
Platform: UNKNOWN
Classifier: Programming Language :: Python :: 3
Classifier: License :: OSI Approved :: MIT License
Classifier: Operating System :: OS Independent
Requires-Python: >=3.6
